augeias/__init__.py
augeias/uri.py
augeias/views.py
augeias/collections/__init__.py
augeias/collections/model.py
augeias/scaffolds/__init__.py
augeias/scaffolds/augeias_scaffold/CHANGES.txt_tmpl
augeias/scaffolds/augeias_scaffold/MANIFEST.in_tmpl
augeias/scaffolds/augeias_scaffold/README.txt_tmpl
augeias/scaffolds/augeias_scaffold/development.ini_tmpl
augeias/scaffolds/augeias_scaffold/requirements-dev.txt_tmpl
augeias/scaffolds/augeias_scaffold/requirements.txt_tmpl
augeias/scaffolds/augeias_scaffold/setup.py_tmpl
augeias/scaffolds/augeias_scaffold/+package+/__init__.py_tmpl
augeias/scaffolds/augeias_scaffold/+package+/collections/__init__.py
augeias/stores/CephStore.py
augeias/stores/PairTreeFileSystemStore.py
augeias/stores/StoreInterface.py
augeias/stores/__init__.py
augeias/stores/error.py
tests/__init__.py
tests/test_errors.py
tests/test_functional.py
tests/test_stores.py
tests/test_uri.py
tests/test_views.py
augeias-0.9.0.dist-info/LICENSE
augeias-0.9.0.dist-info/METADATA
augeias-0.9.0.dist-info/WHEEL
augeias-0.9.0.dist-info/entry_points.txt
augeias-0.9.0.dist-info/top_level.txt
augeias-0.9.0.dist-info/RECORD
