Metadata-Version: 2.1
Name: augeias
Version: 0.9.0
Summary: Augeias. Stores your files.
Home-page: https://augeias.readthedocs.org
Author: Flanders Heritage Agency
Author-email: ict@onroerenderfgoed.be
License: GPLv3
Keywords: web pyramid digital object storage
Classifier: License :: OSI Approved :: GNU General Public License v3 (GPLv3)
Classifier: Programming Language :: Python
Classifier: Framework :: Pyramid
Classifier: Topic :: Internet :: WWW/HTTP
Classifier: Topic :: Internet :: WWW/HTTP :: WSGI :: Application
Classifier: Programming Language :: Python :: 3.6
Classifier: Programming Language :: Python :: 3.7
Classifier: Programming Language :: Python :: 3.8
Requires-Python: >=3.6
License-File: LICENSE
Requires-Dist: pyramid
Requires-Dist: ez-setup (==0.9)
Requires-Dist: pairtree (==0.8.1)
Requires-Dist: python-magic
Requires-Dist: pyramid-rewrite
